{
  "$schema": "http://json-schema.org/draft-07/schema#",
  "type": "object",
  "patternProperties": {
    "^.*$": {
      "type": "object",
      "properties": {
        "dependencies": { "$ref": "#/definitions/dependencies" },
        "peerDependencies": { "$ref": "#/definitions/dependencies" },
        "devDependencies": { "$ref": "#/definitions/dependencies" },
        "env": {
          "$ref": "./env.json"
        }
      }
    }
  },
  "definitions": {
    "dependencies": {
      "type": "object",
      "patternProperties": {
        "^.*$": {
          "type": "string"
        }
      }
    }
  }
}
